witch_doctor/__init__.py
witch_doctor-1.2.1.dist-info/LICENSE
witch_doctor-1.2.1.dist-info/METADATA
witch_doctor-1.2.1.dist-info/WHEEL
witch_doctor-1.2.1.dist-info/RECORD
