Metadata-Version: 2.3
Name: witch-doctor
Version: 1.2.1
Summary: Dependency injection for python
License: Apache-2.0
Author: Marco Sievers de Almeida Ximit Gaia
Author-email: im.ximit@gmail.com
Requires-Python: >=3.10,<4.0
Classifier: License :: OSI Approved :: Apache Software License
Classifier: Programming Language :: Python :: 3
Classifier: Programming Language :: Python :: 3.10
Classifier: Programming Language :: Python :: 3.11
Classifier: Programming Language :: Python :: 3.12
Classifier: Programming Language :: Python :: 3.13
Project-URL: bugs, https://github.com/CenturyBoys/witch-doctor/issues
Project-URL: documentation, https://github.com/CenturyBoys/witch-doctor/blob/main/README.md
Project-URL: homepage, https://github.com/CenturyBoys/witch-doctor
Project-URL: repository, https://github.com/CenturyBoys/witch-doctor/tree/main
